iir_filter.py
py_iir_filter-1.0.5.dist-info/LICENSE
py_iir_filter-1.0.5.dist-info/METADATA
py_iir_filter-1.0.5.dist-info/WHEEL
py_iir_filter-1.0.5.dist-info/top_level.txt
py_iir_filter-1.0.5.dist-info/RECORD
