Metadata-Version: 2.1
Name: py-iir-filter
Version: 1.0.5
Summary: Fast realtime IIR filter
Home-page: https://github.com/berndporr/py-iir-filter
Author: Bernd Porr
Author-email: mail@berndporr.me.uk
License: GPL 3.0
Platform: UNKNOWN
Classifier: Intended Audience :: Developers
Classifier: Operating System :: OS Independent
Classifier: Programming Language :: Python :: 3
Requires-Dist: numpy
